{
    "**********POKEDEX DATA**********": "**********POKEDEX DATA**********",
    "Name": "Buzzwole",
    "ID": 794,
    "Types": [
        "Bug",
        "Fighting"
    ],
    "Species": "Swollen Pokemon",
    "Height": 2.4,
    "Weight": 333.6,
    "Abilities": [
        "Beast Boost"
    ],
    "Evolution": [],
    "Forms": {},
    "**********BASE STATS**********": "**********BASE STATS**********",
    "BaseStats": {
        "HP": 107,
        "Attack": 139,
        "Defense": 139,
        "Special Attack": 53,
        "Special Defense": 70,
        "Speed": 79
    },
    "**********TRAINING**********": "**********TRAINING**********",
    "EV Yeld": {
        "HP": 0,
        "Attack": 1,
        "Defense": 2,
        "Special Attack": 0,
        "Special Defense": 0,
        "Speed": 0
    },
    "Capture Rate": 45,
    "Base Friendship": 0,
    "Base Exp": 257,
    "Experience Group": "Slow",
    "**********BREEDING**********": "**********BREEDING**********",
    "Egg Groups": [
        "Undiscovered"
    ],
    "Female Rate": -1,
    "Egg Cycles": 120,
    "**********SPRITES**********": "**********SPRITES**********",
    "SpriteFScale": 1,
    "SpriteOScale": 1,
    "SpriteBScale": 1
}